huaweicloudsdkidentitycenter/__init__.py
huaweicloudsdkidentitycenter/v1/__init__.py
huaweicloudsdkidentitycenter/v1/identitycenter_async_client.py
huaweicloudsdkidentitycenter/v1/identitycenter_client.py
huaweicloudsdkidentitycenter/v1/model/__init__.py
huaweicloudsdkidentitycenter/v1/model/access_control_attribute_dto.py
huaweicloudsdkidentitycenter/v1/model/access_control_attribute_value_dto.py
huaweicloudsdkidentitycenter/v1/model/account_assignment_dto.py
huaweicloudsdkidentitycenter/v1/model/account_assignment_operation_status_dto.py
huaweicloudsdkidentitycenter/v1/model/account_assignment_operation_status_metadata_dto.py
huaweicloudsdkidentitycenter/v1/model/application_assignment_dto.py
huaweicloudsdkidentitycenter/v1/model/application_dto.py
huaweicloudsdkidentitycenter/v1/model/application_instance_dto.py
huaweicloudsdkidentitycenter/v1/model/application_profile_dto.py
huaweicloudsdkidentitycenter/v1/model/application_provider_dto.py
huaweicloudsdkidentitycenter/v1/model/application_template_display_dto.py
huaweicloudsdkidentitycenter/v1/model/application_template_dto.py
huaweicloudsdkidentitycenter/v1/model/assignment_config_dto.py
huaweicloudsdkidentitycenter/v1/model/attach_managed_policy_to_permission_set_req_body.py
huaweicloudsdkidentitycenter/v1/model/attach_managed_policy_to_permission_set_request.py
huaweicloudsdkidentitycenter/v1/model/attach_managed_policy_to_permission_set_response.py
huaweicloudsdkidentitycenter/v1/model/attach_managed_role_to_permission_set_request.py
huaweicloudsdkidentitycenter/v1/model/attach_managed_role_to_permission_set_response.py
huaweicloudsdkidentitycenter/v1/model/attached_managed_policy_dto.py
huaweicloudsdkidentitycenter/v1/model/certificate_dto.py
huaweicloudsdkidentitycenter/v1/model/consumers_dto.py
huaweicloudsdkidentitycenter/v1/model/create_account_assignment_req_body.py
huaweicloudsdkidentitycenter/v1/model/create_account_assignment_request.py
huaweicloudsdkidentitycenter-3.1.184.dist-info/METADATA
huaweicloudsdkidentitycenter-3.1.184.dist-info/WHEEL
huaweicloudsdkidentitycenter-3.1.184.dist-info/licenses/LICENSE
huaweicloudsdkidentitycenter-3.1.184.dist-info/RECORD
